package_test111111/__init__.py
package_test111111-1.3.5.dist-info/METADATA
package_test111111-1.3.5.dist-info/WHEEL
package_test111111-1.3.5.dist-info/top_level.txt
package_test111111-1.3.5.dist-info/RECORD
